haplohub/__init__.py
haplohub/_version.py
haplohub/api_client.py
haplohub/api_response.py
haplohub/configuration.py
haplohub/exceptions.py
haplohub/py.typed
haplohub/rest.py
haplohub/api/__init__.py
haplohub/api/accession_api.py
haplohub/api/algorithm_api.py
haplohub/api/algorithm_result_api.py
haplohub/api/algorithm_version_api.py
haplohub/api/api_key_api.py
haplohub/api/biomarker_api.py
haplohub/api/biomarker_result_api.py
haplohub/api/cohort_api.py
haplohub/api/config_api.py
haplohub/api/default_api.py
haplohub/api/environment_api.py
haplohub/api/environments_api.py
haplohub/api/file_api.py
haplohub/api/log_api.py
haplohub/api/member_api.py
haplohub/api/member_pgs_score_api.py
haplohub/api/member_report_api.py
haplohub/api/metadata_api.py
haplohub/api/model_api.py
haplohub/api/prediction_api.py
haplohub/api/report_api.py
haplohub/api/report_template_api.py
haplohub/api/sample_api.py
haplohub/api/sample_file_api.py
haplohub/api/trait_api.py
haplohub/api/trait_category_api.py
haplohub/api/upload_api.py
haplohub/api/user_api.py
haplohub/api/variant_api.py
haplohub/api/workflow_api.py
haplohub/models/__init__.py
haplohub/models/accession_schema.py
haplohub/models/algorithm_id.py
haplohub/models/algorithm_result_id.py
haplohub/models/algorithm_result_schema.py
haplohub/models/algorithm_result_status.py
haplohub/models/algorithm_schema.py
haplohub/models/algorithm_version_id.py
haplohub/models/algorithm_version_id1.py
haplohub/models/algorithm_version_schema.py
haplohub/models/api_key_schema.py
haplohub/models/auth_schema.py
haplohub/models/biomarker_result_schema.py
haplohub/models/check_slug_request.py
haplohub/models/cli_schema.py
haplohub/models/cohort_detail_schema.py
haplohub/models/cohort_id.py
haplohub/models/cohort_id1.py
haplohub/models/cohort_schema.py
haplohub/models/config_schema.py
haplohub/models/create_algorithm_result_request.py
haplohub/models/create_algorithm_result_response.py
haplohub/models/create_api_key_schema.py
haplohub-1.0.17.dist-info/licenses/LICENSE
haplohub-1.0.17.dist-info/METADATA
haplohub-1.0.17.dist-info/WHEEL
haplohub-1.0.17.dist-info/top_level.txt
haplohub-1.0.17.dist-info/RECORD
