Metadata-Version: 2.4
Name: haplohub
Version: 1.0.17
Summary: HaploHub API
Author-email: Mike Polcari <mike@haplotype-labs.com>, Ilya Khrustalev <ilya@haplotype-labs.com>
License: 
Project-URL: Source, https://github.com/haplotypelabs/haplohub-python
Keywords: Haplohub,HaploHub API
Classifier: Programming Language :: Python :: 3.8
Classifier: Programming Language :: Python :: 3.9
Classifier: Programming Language :: Python :: 3.10
Classifier: Programming Language :: Python :: 3.11
Classifier: Programming Language :: Python :: 3.12
Classifier: Programming Language :: Python :: 3.13
Requires-Python: >=3.8
License-File: LICENSE
Requires-Dist: urllib3>=1.25.3
Requires-Dist: python-dateutil>=2.8.2
Requires-Dist: pydantic<2,>=1.10.5
Requires-Dist: aenum>=3.1.11
Dynamic: license-file
